{
  "resourceType": "Bundle",
  "type": "batch",
  "entry": [ {
    "fullUrl": "urn:uuid:1382083f-082e-3567-9141-e4829c9ffd8d",
    "resource": {
      "resourceType": "Organization",
      "id": "1382083f-082e-3567-9141-e4829c9ffd8d",
      "meta": {
        "profile": [ "http://hl7.org/fhir/us/core/StructureDefinition/us-core-organization" ]
      },
      "extension": [ {
        "url": "http://synthetichealth.github.io/synthea/utilization-encounters-extension",
        "valueInteger": 1
      }, {
        "url": "http://synthetichealth.github.io/synthea/utilization-procedures-extension",
        "valueInteger": 0
      }, {
        "url": "http://synthetichealth.github.io/synthea/utilization-labs-extension",
        "valueInteger": 0
      }, {
        "url": "http://synthetichealth.github.io/synthea/utilization-prescriptions-extension",
        "valueInteger": 0
      } ],
      "identifier": [ {
        "system": "https://github.com/synthetichealth/synthea",
        "value": "1382083f-082e-3567-9141-e4829c9ffd8d"
      } ],
      "active": true,
      "type": [ {
        "coding": [ {
          "system": "http://terminology.hl7.org/CodeSystem/organization-type",
          "code": "prov",
          "display": "Healthcare Provider"
        } ],
        "text": "Healthcare Provider"
      } ],
      "name": "1 WORLD MEDICINE URGENT CARE CORP",
      "telecom": [ {
        "system": "phone",
        "value": "6265723688"
      } ],
      "address": [ {
        "line": [ "925 S GARFIELD AVE" ],
        "city": "ALHAMBRA",
        "state": "CA",
        "postalCode": "918014442",
        "country": "US"
      } ]
    },
    "request": {
      "method": "POST",
      "url": "Organization",
      "ifNoneExist": "identifier=https://github.com/synthetichealth/synthea|1382083f-082e-3567-9141-e4829c9ffd8d"
    }
  }, {
    "fullUrl": "urn:uuid:4993677d-5348-3106-9fad-6c7b1722840b",
    "resource": {
      "resourceType": "Location",
      "id": "4993677d-5348-3106-9fad-6c7b1722840b",
      "meta": {
        "profile": [ "http://hl7.org/fhir/us/core/StructureDefinition/us-core-location" ]
      },
      "identifier": [ {
        "system": "https://github.com/synthetichealth/synthea",
        "value": "4993677d-5348-3106-9fad-6c7b1722840b"
      } ],
      "status": "active",
      "name": "1 WORLD MEDICINE URGENT CARE CORP",
      "telecom": [ {
        "system": "phone",
        "value": "6265723688"
      } ],
      "address": {
        "line": [ "925 S GARFIELD AVE" ],
        "city": "ALHAMBRA",
        "state": "CA",
        "postalCode": "918014442",
        "country": "US"
      },
      "position": {
        "longitude": -118.12315104545455,
        "latitude": 34.085471909090906
      },
      "managingOrganization": {
        "identifier": {
          "system": "https://github.com/synthetichealth/synthea",
          "value": "1382083f-082e-3567-9141-e4829c9ffd8d"
        },
        "display": "1 WORLD MEDICINE URGENT CARE CORP"
      }
    },
    "request": {
      "method": "POST",
      "url": "Location",
      "ifNoneExist": "identifier=https://github.com/synthetichealth/synthea|4993677d-5348-3106-9fad-6c7b1722840b"
    }
  }, {
    "fullUrl": "urn:uuid:38fcc1cb-6c6e-31c3-9aec-b73a06136c88",
    "resource": {
      "resourceType": "Organization",
      "id": "38fcc1cb-6c6e-31c3-9aec-b73a06136c88",
      "meta": {
        "profile": [ "http://hl7.org/fhir/us/core/StructureDefinition/us-core-organization" ]
      },
      "extension": [ {
        "url": "http://synthetichealth.github.io/synthea/utilization-encounters-extension",
        "valueInteger": 56
      }, {
        "url": "http://synthetichealth.github.io/synthea/utilization-procedures-extension",
        "valueInteger": 0
      }, {
        "url": "http://synthetichealth.github.io/synthea/utilization-labs-extension",
        "valueInteger": 0
      }, {
        "url": "http://synthetichealth.github.io/synthea/utilization-prescriptions-extension",
        "valueInteger": 0
      } ],
      "identifier": [ {
        "system": "https://github.com/synthetichealth/synthea",
        "value": "38fcc1cb-6c6e-31c3-9aec-b73a06136c88"
      } ],
      "active": true,
      "type": [ {
        "coding": [ {
          "system": "http://terminology.hl7.org/CodeSystem/organization-type",
          "code": "prov",
          "display": "Healthcare Provider"
        } ],
        "text": "Healthcare Provider"
      } ],
      "name": "AHMC SAN GABRIEL VALLEY MEDICAL",
      "telecom": [ {
        "system": "phone",
        "value": "6262895454"
      } ],
      "address": [ {
        "line": [ "438 W LAS TUNAS DR" ],
        "city": "SAN GABRIEL",
        "state": "CA",
        "postalCode": "917761216",
        "country": "US"
      } ]
    },
    "request": {
      "method": "POST",
      "url": "Organization",
      "ifNoneExist": "identifier=https://github.com/synthetichealth/synthea|38fcc1cb-6c6e-31c3-9aec-b73a06136c88"
    }
  }, {
    "fullUrl": "urn:uuid:cd86efec-a836-3784-bb7e-198e16845388",
    "resource": {
      "resourceType": "Location",
      "id": "cd86efec-a836-3784-bb7e-198e16845388",
      "meta": {
        "profile": [ "http://hl7.org/fhir/us/core/StructureDefinition/us-core-location" ]
      },
      "identifier": [ {
        "system": "https://github.com/synthetichealth/synthea",
        "value": "cd86efec-a836-3784-bb7e-198e16845388"
      } ],
      "status": "active",
      "name": "AHMC SAN GABRIEL VALLEY MEDICAL",
      "telecom": [ {
        "system": "phone",
        "value": "6262895454"
      } ],
      "address": {
        "line": [ "438 W LAS TUNAS DR" ],
        "city": "SAN GABRIEL",
        "state": "CA",
        "postalCode": "917761216",
        "country": "US"
      },
      "position": {
        "longitude": -118.10587972761789,
        "latitude": 34.10094775
      },
      "managingOrganization": {
        "identifier": {
          "system": "https://github.com/synthetichealth/synthea",
          "value": "38fcc1cb-6c6e-31c3-9aec-b73a06136c88"
        },
        "display": "AHMC SAN GABRIEL VALLEY MEDICAL"
      }
    },
    "request": {
      "method": "POST",
      "url": "Location",
      "ifNoneExist": "identifier=https://github.com/synthetichealth/synthea|cd86efec-a836-3784-bb7e-198e16845388"
    }
  }, {
    "fullUrl": "urn:uuid:8a171cbd-77fd-3b06-94f4-9233ec3063a3",
    "resource": {
      "resourceType": "Organization",
      "id": "8a171cbd-77fd-3b06-94f4-9233ec3063a3",
      "meta": {
        "profile": [ "http://hl7.org/fhir/us/core/StructureDefinition/us-core-organization" ]
      },
      "extension": [ {
        "url": "http://synthetichealth.github.io/synthea/utilization-encounters-extension",
        "valueInteger": 25
      }, {
        "url": "http://synthetichealth.github.io/synthea/utilization-procedures-extension",
        "valueInteger": 0
      }, {
        "url": "http://synthetichealth.github.io/synthea/utilization-labs-extension",
        "valueInteger": 0
      }, {
        "url": "http://synthetichealth.github.io/synthea/utilization-prescriptions-extension",
        "valueInteger": 0
      } ],
      "identifier": [ {
        "system": "https://github.com/synthetichealth/synthea",
        "value": "8a171cbd-77fd-3b06-94f4-9233ec3063a3"
      } ],
      "active": true,
      "type": [ {
        "coding": [ {
          "system": "http://terminology.hl7.org/CodeSystem/organization-type",
          "code": "prov",
          "display": "Healthcare Provider"
        } ],
        "text": "Healthcare Provider"
      } ],
      "name": "SAN GABRIEL VALLEY MEDICAL CENTER",
      "telecom": [ {
        "system": "phone",
        "value": "6262895454"
      } ],
      "address": [ {
        "line": [ "438 W LAS TUNAS DR" ],
        "city": "SAN GABRIEL",
        "state": "CA",
        "postalCode": "917761216",
        "country": "US"
      } ]
    },
    "request": {
      "method": "POST",
      "url": "Organization",
      "ifNoneExist": "identifier=https://github.com/synthetichealth/synthea|8a171cbd-77fd-3b06-94f4-9233ec3063a3"
    }
  }, {
    "fullUrl": "urn:uuid:d813e4d4-ffbc-398b-b521-000155a06d70",
    "resource": {
      "resourceType": "Location",
      "id": "d813e4d4-ffbc-398b-b521-000155a06d70",
      "meta": {
        "profile": [ "http://hl7.org/fhir/us/core/StructureDefinition/us-core-location" ]
      },
      "identifier": [ {
        "system": "https://github.com/synthetichealth/synthea",
        "value": "d813e4d4-ffbc-398b-b521-000155a06d70"
      } ],
      "status": "active",
      "name": "SAN GABRIEL VALLEY MEDICAL CENTER",
      "telecom": [ {
        "system": "phone",
        "value": "6262895454"
      } ],
      "address": {
        "line": [ "438 W LAS TUNAS DR" ],
        "city": "SAN GABRIEL",
        "state": "CA",
        "postalCode": "917761216",
        "country": "US"
      },
      "position": {
        "longitude": -118.10587972761789,
        "latitude": 34.10094775
      },
      "managingOrganization": {
        "identifier": {
          "system": "https://github.com/synthetichealth/synthea",
          "value": "8a171cbd-77fd-3b06-94f4-9233ec3063a3"
        },
        "display": "SAN GABRIEL VALLEY MEDICAL CENTER"
      }
    },
    "request": {
      "method": "POST",
      "url": "Location",
      "ifNoneExist": "identifier=https://github.com/synthetichealth/synthea|d813e4d4-ffbc-398b-b521-000155a06d70"
    }
  }, {
    "fullUrl": "urn:uuid:357e84ea-e14e-30ef-b6ce-5c0e3323d836",
    "resource": {
      "resourceType": "Organization",
      "id": "357e84ea-e14e-30ef-b6ce-5c0e3323d836",
      "meta": {
        "profile": [ "http://hl7.org/fhir/us/core/StructureDefinition/us-core-organization" ]
      },
      "extension": [ {
        "url": "http://synthetichealth.github.io/synthea/utilization-encounters-extension",
        "valueInteger": 46
      }, {
        "url": "http://synthetichealth.github.io/synthea/utilization-procedures-extension",
        "valueInteger": 363
      }, {
        "url": "http://synthetichealth.github.io/synthea/utilization-labs-extension",
        "valueInteger": 83
      }, {
        "url": "http://synthetichealth.github.io/synthea/utilization-prescriptions-extension",
        "valueInteger": 66
      } ],
      "identifier": [ {
        "system": "https://github.com/synthetichealth/synthea",
        "value": "357e84ea-e14e-30ef-b6ce-5c0e3323d836"
      } ],
      "active": true,
      "type": [ {
        "coding": [ {
          "system": "http://terminology.hl7.org/CodeSystem/organization-type",
          "code": "prov",
          "display": "Healthcare Provider"
        } ],
        "text": "Healthcare Provider"
      } ],
      "name": "GARDNER FAMILY HEALTH NETWORK INC",
      "telecom": [ {
        "system": "phone",
        "value": "4082002291"
      } ],
      "address": [ {
        "line": [ "3351 EL CAMINO REAL" ],
        "city": "ATHERTON",
        "state": "CA",
        "postalCode": "940273802",
        "country": "US"
      } ]
    },
    "request": {
      "method": "POST",
      "url": "Organization",
      "ifNoneExist": "identifier=https://github.com/synthetichealth/synthea|357e84ea-e14e-30ef-b6ce-5c0e3323d836"
    }
  }, {
    "fullUrl": "urn:uuid:69a38807-1884-3a08-98e2-be34a213c33f",
    "resource": {
      "resourceType": "Location",
      "id": "69a38807-1884-3a08-98e2-be34a213c33f",
      "meta": {
        "profile": [ "http://hl7.org/fhir/us/core/StructureDefinition/us-core-location" ]
      },
      "identifier": [ {
        "system": "https://github.com/synthetichealth/synthea",
        "value": "69a38807-1884-3a08-98e2-be34a213c33f"
      } ],
      "status": "active",
      "name": "GARDNER FAMILY HEALTH NETWORK INC",
      "telecom": [ {
        "system": "phone",
        "value": "4082002291"
      } ],
      "address": {
        "line": [ "3351 EL CAMINO REAL" ],
        "city": "ATHERTON",
        "state": "CA",
        "postalCode": "940273802",
        "country": "US"
      },
      "position": {
        "longitude": -122.20701236922542,
        "latitude": 37.466178
      },
      "managingOrganization": {
        "identifier": {
          "system": "https://github.com/synthetichealth/synthea",
          "value": "357e84ea-e14e-30ef-b6ce-5c0e3323d836"
        },
        "display": "GARDNER FAMILY HEALTH NETWORK INC"
      }
    },
    "request": {
      "method": "POST",
      "url": "Location",
      "ifNoneExist": "identifier=https://github.com/synthetichealth/synthea|69a38807-1884-3a08-98e2-be34a213c33f"
    }
  }, {
    "fullUrl": "urn:uuid:e0f26723-98aa-3dbc-a36c-e4237c47daa9",
    "resource": {
      "resourceType": "Organization",
      "id": "e0f26723-98aa-3dbc-a36c-e4237c47daa9",
      "meta": {
        "profile": [ "http://hl7.org/fhir/us/core/StructureDefinition/us-core-organization" ]
      },
      "extension": [ {
        "url": "http://synthetichealth.github.io/synthea/utilization-encounters-extension",
        "valueInteger": 1
      }, {
        "url": "http://synthetichealth.github.io/synthea/utilization-procedures-extension",
        "valueInteger": 0
      }, {
        "url": "http://synthetichealth.github.io/synthea/utilization-labs-extension",
        "valueInteger": 0
      }, {
        "url": "http://synthetichealth.github.io/synthea/utilization-prescriptions-extension",
        "valueInteger": 0
      } ],
      "identifier": [ {
        "system": "https://github.com/synthetichealth/synthea",
        "value": "e0f26723-98aa-3dbc-a36c-e4237c47daa9"
      } ],
      "active": true,
      "type": [ {
        "coding": [ {
          "system": "http://terminology.hl7.org/CodeSystem/organization-type",
          "code": "prov",
          "display": "Healthcare Provider"
        } ],
        "text": "Healthcare Provider"
      } ],
      "name": "LA VETA HEALTHCARE, INC.",
      "telecom": [ {
        "system": "phone",
        "value": "7149786800"
      } ],
      "address": [ {
        "line": [ "1835 W LA VETA AVE" ],
        "city": "ORANGE",
        "state": "CA",
        "postalCode": "928684132",
        "country": "US"
      } ]
    },
    "request": {
      "method": "POST",
      "url": "Organization",
      "ifNoneExist": "identifier=https://github.com/synthetichealth/synthea|e0f26723-98aa-3dbc-a36c-e4237c47daa9"
    }
  }, {
    "fullUrl": "urn:uuid:af43fef4-5d41-336d-be38-04b0827caea1",
    "resource": {
      "resourceType": "Location",
      "id": "af43fef4-5d41-336d-be38-04b0827caea1",
      "meta": {
        "profile": [ "http://hl7.org/fhir/us/core/StructureDefinition/us-core-location" ]
      },
      "identifier": [ {
        "system": "https://github.com/synthetichealth/synthea",
        "value": "af43fef4-5d41-336d-be38-04b0827caea1"
      } ],
      "status": "active",
      "name": "LA VETA HEALTHCARE, INC.",
      "telecom": [ {
        "system": "phone",
        "value": "7149786800"
      } ],
      "address": {
        "line": [ "1835 W LA VETA AVE" ],
        "city": "ORANGE",
        "state": "CA",
        "postalCode": "928684132",
        "country": "US"
      },
      "position": {
        "longitude": -117.87238832846234,
        "latitude": 33.78043327669826
      },
      "managingOrganization": {
        "identifier": {
          "system": "https://github.com/synthetichealth/synthea",
          "value": "e0f26723-98aa-3dbc-a36c-e4237c47daa9"
        },
        "display": "LA VETA HEALTHCARE, INC."
      }
    },
    "request": {
      "method": "POST",
      "url": "Location",
      "ifNoneExist": "identifier=https://github.com/synthetichealth/synthea|af43fef4-5d41-336d-be38-04b0827caea1"
    }
  }, {
    "fullUrl": "urn:uuid:1d9bb5c2-52e4-31a2-bf71-7be8772816d5",
    "resource": {
      "resourceType": "Organization",
      "id": "1d9bb5c2-52e4-31a2-bf71-7be8772816d5",
      "meta": {
        "profile": [ "http://hl7.org/fhir/us/core/StructureDefinition/us-core-organization" ]
      },
      "extension": [ {
        "url": "http://synthetichealth.github.io/synthea/utilization-encounters-extension",
        "valueInteger": 6
      }, {
        "url": "http://synthetichealth.github.io/synthea/utilization-procedures-extension",
        "valueInteger": 0
      }, {
        "url": "http://synthetichealth.github.io/synthea/utilization-labs-extension",
        "valueInteger": 0
      }, {
        "url": "http://synthetichealth.github.io/synthea/utilization-prescriptions-extension",
        "valueInteger": 0
      }, {
        "url": "http://synthetichealth.github.io/synthea/bed-count-extension",
        "valueInteger": 59
      } ],
      "identifier": [ {
        "system": "https://github.com/synthetichealth/synthea",
        "value": "1d9bb5c2-52e4-31a2-bf71-7be8772816d5"
      } ],
      "active": true,
      "type": [ {
        "coding": [ {
          "system": "http://terminology.hl7.org/CodeSystem/organization-type",
          "code": "prov",
          "display": "Healthcare Provider"
        } ],
        "text": "Healthcare Provider"
      } ],
      "name": "BROADWAY HEALTHCARE CENTER",
      "telecom": [ {
        "system": "phone",
        "value": "6262852165"
      } ],
      "address": [ {
        "line": [ "112 E. BROADWAY" ],
        "city": "SAN GABRIEL",
        "state": "CA",
        "postalCode": "917761805",
        "country": "US"
      } ]
    },
    "request": {
      "method": "POST",
      "url": "Organization",
      "ifNoneExist": "identifier=https://github.com/synthetichealth/synthea|1d9bb5c2-52e4-31a2-bf71-7be8772816d5"
    }
  }, {
    "fullUrl": "urn:uuid:e4f92f49-03ff-3c62-afd1-66655f1743eb",
    "resource": {
      "resourceType": "Location",
      "id": "e4f92f49-03ff-3c62-afd1-66655f1743eb",
      "meta": {
        "profile": [ "http://hl7.org/fhir/us/core/StructureDefinition/us-core-location" ]
      },
      "identifier": [ {
        "system": "https://github.com/synthetichealth/synthea",
        "value": "e4f92f49-03ff-3c62-afd1-66655f1743eb"
      } ],
      "status": "active",
      "name": "BROADWAY HEALTHCARE CENTER",
      "telecom": [ {
        "system": "phone",
        "value": "6262852165"
      } ],
      "address": {
        "line": [ "112 E. BROADWAY" ],
        "city": "SAN GABRIEL",
        "state": "CA",
        "postalCode": "917761805",
        "country": "US"
      },
      "position": {
        "longitude": -118.1024071,
        "latitude": 34.0988593
      },
      "managingOrganization": {
        "identifier": {
          "system": "https://github.com/synthetichealth/synthea",
          "value": "1d9bb5c2-52e4-31a2-bf71-7be8772816d5"
        },
        "display": "BROADWAY HEALTHCARE CENTER"
      }
    },
    "request": {
      "method": "POST",
      "url": "Location",
      "ifNoneExist": "identifier=https://github.com/synthetichealth/synthea|e4f92f49-03ff-3c62-afd1-66655f1743eb"
    }
  }, {
    "fullUrl": "urn:uuid:4a14ecf6-3388-327e-ad27-4c07c67a8160",
    "resource": {
      "resourceType": "Organization",
      "id": "4a14ecf6-3388-327e-ad27-4c07c67a8160",
      "meta": {
        "profile": [ "http://hl7.org/fhir/us/core/StructureDefinition/us-core-organization" ]
      },
      "extension": [ {
        "url": "http://synthetichealth.github.io/synthea/utilization-encounters-extension",
        "valueInteger": 35
      }, {
        "url": "http://synthetichealth.github.io/synthea/utilization-procedures-extension",
        "valueInteger": 243
      }, {
        "url": "http://synthetichealth.github.io/synthea/utilization-labs-extension",
        "valueInteger": 34
      }, {
        "url": "http://synthetichealth.github.io/synthea/utilization-prescriptions-extension",
        "valueInteger": 16
      } ],
      "identifier": [ {
        "system": "https://github.com/synthetichealth/synthea",
        "value": "4a14ecf6-3388-327e-ad27-4c07c67a8160"
      } ],
      "active": true,
      "type": [ {
        "coding": [ {
          "system": "http://terminology.hl7.org/CodeSystem/organization-type",
          "code": "prov",
          "display": "Healthcare Provider"
        } ],
        "text": "Healthcare Provider"
      } ],
      "name": "JOHN K. FLYNN COMMUNITY CLINIC",
      "telecom": [ {
        "system": "phone",
        "value": "8059836644"
      } ],
      "address": [ {
        "line": [ "3100 NORTH ROSE AVENUE" ],
        "city": "OXNARD",
        "state": "CA",
        "postalCode": "930361807",
        "country": "US"
      } ]
    },
    "request": {
      "method": "POST",
      "url": "Organization",
      "ifNoneExist": "identifier=https://github.com/synthetichealth/synthea|4a14ecf6-3388-327e-ad27-4c07c67a8160"
    }
  }, {
    "fullUrl": "urn:uuid:ea75b3ac-2293-326a-9349-92d5d3783a7e",
    "resource": {
      "resourceType": "Location",
      "id": "ea75b3ac-2293-326a-9349-92d5d3783a7e",
      "meta": {
        "profile": [ "http://hl7.org/fhir/us/core/StructureDefinition/us-core-location" ]
      },
      "identifier": [ {
        "system": "https://github.com/synthetichealth/synthea",
        "value": "ea75b3ac-2293-326a-9349-92d5d3783a7e"
      } ],
      "status": "active",
      "name": "JOHN K. FLYNN COMMUNITY CLINIC",
      "telecom": [ {
        "system": "phone",
        "value": "8059836644"
      } ],
      "address": {
        "line": [ "3100 NORTH ROSE AVENUE" ],
        "city": "OXNARD",
        "state": "CA",
        "postalCode": "930361807",
        "country": "US"
      },
      "position": {
        "longitude": -119.1585917,
        "latitude": 34.2230862
      },
      "managingOrganization": {
        "identifier": {
          "system": "https://github.com/synthetichealth/synthea",
          "value": "4a14ecf6-3388-327e-ad27-4c07c67a8160"
        },
        "display": "JOHN K. FLYNN COMMUNITY CLINIC"
      }
    },
    "request": {
      "method": "POST",
      "url": "Location",
      "ifNoneExist": "identifier=https://github.com/synthetichealth/synthea|ea75b3ac-2293-326a-9349-92d5d3783a7e"
    }
  }, {
    "fullUrl": "urn:uuid:4394dc4f-d065-3588-8407-81f86244f7b0",
    "resource": {
      "resourceType": "Organization",
      "id": "4394dc4f-d065-3588-8407-81f86244f7b0",
      "meta": {
        "profile": [ "http://hl7.org/fhir/us/core/StructureDefinition/us-core-organization" ]
      },
      "extension": [ {
        "url": "http://synthetichealth.github.io/synthea/utilization-encounters-extension",
        "valueInteger": 1
      }, {
        "url": "http://synthetichealth.github.io/synthea/utilization-procedures-extension",
        "valueInteger": 0
      }, {
        "url": "http://synthetichealth.github.io/synthea/utilization-labs-extension",
        "valueInteger": 0
      }, {
        "url": "http://synthetichealth.github.io/synthea/utilization-prescriptions-extension",
        "valueInteger": 0
      } ],
      "identifier": [ {
        "system": "https://github.com/synthetichealth/synthea",
        "value": "4394dc4f-d065-3588-8407-81f86244f7b0"
      } ],
      "active": true,
      "type": [ {
        "coding": [ {
          "system": "http://terminology.hl7.org/CodeSystem/organization-type",
          "code": "prov",
          "display": "Healthcare Provider"
        } ],
        "text": "Healthcare Provider"
      } ],
      "name": "OC URGENTCARE MEDICAL GROUP INCORPORATED",
      "telecom": [ {
        "system": "phone",
        "value": "7149915700"
      } ],
      "address": [ {
        "line": [ "631 S BROOKHURST ST" ],
        "city": "SANTA ANA",
        "state": "CA",
        "postalCode": "927053916",
        "country": "US"
      } ]
    },
    "request": {
      "method": "POST",
      "url": "Organization",
      "ifNoneExist": "identifier=https://github.com/synthetichealth/synthea|4394dc4f-d065-3588-8407-81f86244f7b0"
    }
  }, {
    "fullUrl": "urn:uuid:2d5b1584-9d6e-3eb5-982e-c05196023c2f",
    "resource": {
      "resourceType": "Location",
      "id": "2d5b1584-9d6e-3eb5-982e-c05196023c2f",
      "meta": {
        "profile": [ "http://hl7.org/fhir/us/core/StructureDefinition/us-core-location" ]
      },
      "identifier": [ {
        "system": "https://github.com/synthetichealth/synthea",
        "value": "2d5b1584-9d6e-3eb5-982e-c05196023c2f"
      } ],
      "status": "active",
      "name": "OC URGENTCARE MEDICAL GROUP INCORPORATED",
      "telecom": [ {
        "system": "phone",
        "value": "7149915700"
      } ],
      "address": {
        "line": [ "631 S BROOKHURST ST" ],
        "city": "SANTA ANA",
        "state": "CA",
        "postalCode": "927053916",
        "country": "US"
      },
      "position": {
        "longitude": -117.8732213,
        "latitude": 33.7494951
      },
      "managingOrganization": {
        "identifier": {
          "system": "https://github.com/synthetichealth/synthea",
          "value": "4394dc4f-d065-3588-8407-81f86244f7b0"
        },
        "display": "OC URGENTCARE MEDICAL GROUP INCORPORATED"
      }
    },
    "request": {
      "method": "POST",
      "url": "Location",
      "ifNoneExist": "identifier=https://github.com/synthetichealth/synthea|2d5b1584-9d6e-3eb5-982e-c05196023c2f"
    }
  }, {
    "fullUrl": "urn:uuid:9dedbedd-0d1e-34aa-aaae-04c843ae5b2b",
    "resource": {
      "resourceType": "Organization",
      "id": "9dedbedd-0d1e-34aa-aaae-04c843ae5b2b",
      "meta": {
        "profile": [ "http://hl7.org/fhir/us/core/StructureDefinition/us-core-organization" ]
      },
      "extension": [ {
        "url": "http://synthetichealth.github.io/synthea/utilization-encounters-extension",
        "valueInteger": 1
      }, {
        "url": "http://synthetichealth.github.io/synthea/utilization-procedures-extension",
        "valueInteger": 0
      }, {
        "url": "http://synthetichealth.github.io/synthea/utilization-labs-extension",
        "valueInteger": 0
      }, {
        "url": "http://synthetichealth.github.io/synthea/utilization-prescriptions-extension",
        "valueInteger": 0
      } ],
      "identifier": [ {
        "system": "https://github.com/synthetichealth/synthea",
        "value": "9dedbedd-0d1e-34aa-aaae-04c843ae5b2b"
      } ],
      "active": true,
      "type": [ {
        "coding": [ {
          "system": "http://terminology.hl7.org/CodeSystem/organization-type",
          "code": "prov",
          "display": "Healthcare Provider"
        } ],
        "text": "Healthcare Provider"
      } ],
      "name": "VALLEY CARE HOME HEALTH SERVICES, INC",
      "telecom": [ {
        "system": "phone",
        "value": "9516766438"
      } ],
      "address": [ {
        "line": [ "ONE RIDGEGATE DRIVE, SUITE #230" ],
        "city": "TEMECULA",
        "state": "CA",
        "postalCode": "925905507",
        "country": "US"
      } ]
    },
    "request": {
      "method": "POST",
      "url": "Organization",
      "ifNoneExist": "identifier=https://github.com/synthetichealth/synthea|9dedbedd-0d1e-34aa-aaae-04c843ae5b2b"
    }
  }, {
    "fullUrl": "urn:uuid:8f791ae1-f66c-3780-aab8-66d941efdbfc",
    "resource": {
      "resourceType": "Location",
      "id": "8f791ae1-f66c-3780-aab8-66d941efdbfc",
      "meta": {
        "profile": [ "http://hl7.org/fhir/us/core/StructureDefinition/us-core-location" ]
      },
      "identifier": [ {
        "system": "https://github.com/synthetichealth/synthea",
        "value": "8f791ae1-f66c-3780-aab8-66d941efdbfc"
      } ],
      "status": "active",
      "name": "VALLEY CARE HOME HEALTH SERVICES, INC",
      "telecom": [ {
        "system": "phone",
        "value": "9516766438"
      } ],
      "address": {
        "line": [ "ONE RIDGEGATE DRIVE, SUITE #230" ],
        "city": "TEMECULA",
        "state": "CA",
        "postalCode": "925905507",
        "country": "US"
      },
      "position": {
        "longitude": -117.1473661,
        "latitude": 33.4946353
      },
      "managingOrganization": {
        "identifier": {
          "system": "https://github.com/synthetichealth/synthea",
          "value": "9dedbedd-0d1e-34aa-aaae-04c843ae5b2b"
        },
        "display": "VALLEY CARE HOME HEALTH SERVICES, INC"
      }
    },
    "request": {
      "method": "POST",
      "url": "Location",
      "ifNoneExist": "identifier=https://github.com/synthetichealth/synthea|8f791ae1-f66c-3780-aab8-66d941efdbfc"
    }
  }, {
    "fullUrl": "urn:uuid:1b2ef18e-e364-315a-8484-5c07f5b0895e",
    "resource": {
      "resourceType": "Organization",
      "id": "1b2ef18e-e364-315a-8484-5c07f5b0895e",
      "meta": {
        "profile": [ "http://hl7.org/fhir/us/core/StructureDefinition/us-core-organization" ]
      },
      "extension": [ {
        "url": "http://synthetichealth.github.io/synthea/utilization-encounters-extension",
        "valueInteger": 49
      }, {
        "url": "http://synthetichealth.github.io/synthea/utilization-procedures-extension",
        "valueInteger": 0
      }, {
        "url": "http://synthetichealth.github.io/synthea/utilization-labs-extension",
        "valueInteger": 0
      }, {
        "url": "http://synthetichealth.github.io/synthea/utilization-prescriptions-extension",
        "valueInteger": 0
      } ],
      "identifier": [ {
        "system": "https://github.com/synthetichealth/synthea",
        "value": "1b2ef18e-e364-315a-8484-5c07f5b0895e"
      } ],
      "active": true,
      "type": [ {
        "coding": [ {
          "system": "http://terminology.hl7.org/CodeSystem/organization-type",
          "code": "prov",
          "display": "Healthcare Provider"
        } ],
        "text": "Healthcare Provider"
      } ],
      "name": "UNIVERSITY OF CALIFORNIA IRVINE",
      "telecom": [ {
        "system": "phone",
        "value": "7144567295"
      } ],
      "address": [ {
        "line": [ "101 THE CITY DR S" ],
        "city": "ORANGE",
        "state": "CA",
        "postalCode": "928683201",
        "country": "US"
      } ]
    },
    "request": {
      "method": "POST",
      "url": "Organization",
      "ifNoneExist": "identifier=https://github.com/synthetichealth/synthea|1b2ef18e-e364-315a-8484-5c07f5b0895e"
    }
  }, {
    "fullUrl": "urn:uuid:2eea702f-40a2-3299-aea2-3edfee750f5d",
    "resource": {
      "resourceType": "Location",
      "id": "2eea702f-40a2-3299-aea2-3edfee750f5d",
      "meta": {
        "profile": [ "http://hl7.org/fhir/us/core/StructureDefinition/us-core-location" ]
      },
      "identifier": [ {
        "system": "https://github.com/synthetichealth/synthea",
        "value": "2eea702f-40a2-3299-aea2-3edfee750f5d"
      } ],
      "status": "active",
      "name": "UNIVERSITY OF CALIFORNIA IRVINE",
      "telecom": [ {
        "system": "phone",
        "value": "7144567295"
      } ],
      "address": {
        "line": [ "101 THE CITY DR S" ],
        "city": "ORANGE",
        "state": "CA",
        "postalCode": "928683201",
        "country": "US"
      },
      "position": {
        "longitude": -117.88840705261205,
        "latitude": 33.78722845
      },
      "managingOrganization": {
        "identifier": {
          "system": "https://github.com/synthetichealth/synthea",
          "value": "1b2ef18e-e364-315a-8484-5c07f5b0895e"
        },
        "display": "UNIVERSITY OF CALIFORNIA IRVINE"
      }
    },
    "request": {
      "method": "POST",
      "url": "Location",
      "ifNoneExist": "identifier=https://github.com/synthetichealth/synthea|2eea702f-40a2-3299-aea2-3edfee750f5d"
    }
  }, {
    "fullUrl": "urn:uuid:8fb4c789-a977-3026-812c-17f80918205a",
    "resource": {
      "resourceType": "Organization",
      "id": "8fb4c789-a977-3026-812c-17f80918205a",
      "meta": {
        "profile": [ "http://hl7.org/fhir/us/core/StructureDefinition/us-core-organization" ]
      },
      "extension": [ {
        "url": "http://synthetichealth.github.io/synthea/utilization-encounters-extension",
        "valueInteger": 61
      }, {
        "url": "http://synthetichealth.github.io/synthea/utilization-procedures-extension",
        "valueInteger": 0
      }, {
        "url": "http://synthetichealth.github.io/synthea/utilization-labs-extension",
        "valueInteger": 0
      }, {
        "url": "http://synthetichealth.github.io/synthea/utilization-prescriptions-extension",
        "valueInteger": 0
      } ],
      "identifier": [ {
        "system": "https://github.com/synthetichealth/synthea",
        "value": "8fb4c789-a977-3026-812c-17f80918205a"
      } ],
      "active": true,
      "type": [ {
        "coding": [ {
          "system": "http://terminology.hl7.org/CodeSystem/organization-type",
          "code": "prov",
          "display": "Healthcare Provider"
        } ],
        "text": "Healthcare Provider"
      } ],
      "name": "ST JOHNS REGIONAL MEDICAL CENTER",
      "telecom": [ {
        "system": "phone",
        "value": "8059882701"
      } ],
      "address": [ {
        "line": [ "1600 N ROSE AVE" ],
        "city": "PORT HUENEME",
        "state": "CA",
        "postalCode": "930413220",
        "country": "US"
      } ]
    },
    "request": {
      "method": "POST",
      "url": "Organization",
      "ifNoneExist": "identifier=https://github.com/synthetichealth/synthea|8fb4c789-a977-3026-812c-17f80918205a"
    }
  }, {
    "fullUrl": "urn:uuid:6310499b-a7c5-3932-863a-9b5ca2437b94",
    "resource": {
      "resourceType": "Location",
      "id": "6310499b-a7c5-3932-863a-9b5ca2437b94",
      "meta": {
        "profile": [ "http://hl7.org/fhir/us/core/StructureDefinition/us-core-location" ]
      },
      "identifier": [ {
        "system": "https://github.com/synthetichealth/synthea",
        "value": "6310499b-a7c5-3932-863a-9b5ca2437b94"
      } ],
      "status": "active",
      "name": "ST JOHNS REGIONAL MEDICAL CENTER",
      "telecom": [ {
        "system": "phone",
        "value": "8059882701"
      } ],
      "address": {
        "line": [ "1600 N ROSE AVE" ],
        "city": "PORT HUENEME",
        "state": "CA",
        "postalCode": "930413220",
        "country": "US"
      },
      "position": {
        "longitude": -119.1951559,
        "latitude": 34.1477558
      },
      "managingOrganization": {
        "identifier": {
          "system": "https://github.com/synthetichealth/synthea",
          "value": "8fb4c789-a977-3026-812c-17f80918205a"
        },
        "display": "ST JOHNS REGIONAL MEDICAL CENTER"
      }
    },
    "request": {
      "method": "POST",
      "url": "Location",
      "ifNoneExist": "identifier=https://github.com/synthetichealth/synthea|6310499b-a7c5-3932-863a-9b5ca2437b94"
    }
  }, {
    "fullUrl": "urn:uuid:dbbc5a45-af78-3aec-a0b3-d779cf9c325e",
    "resource": {
      "resourceType": "Organization",
      "id": "dbbc5a45-af78-3aec-a0b3-d779cf9c325e",
      "meta": {
        "profile": [ "http://hl7.org/fhir/us/core/StructureDefinition/us-core-organization" ]
      },
      "extension": [ {
        "url": "http://synthetichealth.github.io/synthea/utilization-encounters-extension",
        "valueInteger": 21
      }, {
        "url": "http://synthetichealth.github.io/synthea/utilization-procedures-extension",
        "valueInteger": 0
      }, {
        "url": "http://synthetichealth.github.io/synthea/utilization-labs-extension",
        "valueInteger": 0
      }, {
        "url": "http://synthetichealth.github.io/synthea/utilization-prescriptions-extension",
        "valueInteger": 0
      } ],
      "identifier": [ {
        "system": "https://github.com/synthetichealth/synthea",
        "value": "dbbc5a45-af78-3aec-a0b3-d779cf9c325e"
      } ],
      "active": true,
      "type": [ {
        "coding": [ {
          "system": "http://terminology.hl7.org/CodeSystem/organization-type",
          "code": "prov",
          "display": "Healthcare Provider"
        } ],
        "text": "Healthcare Provider"
      } ],
      "name": "ENCOMPASS HEALTH REHABILITATION HOSPITAL OF MURRIETA, LLC",
      "telecom": [ {
        "system": "phone",
        "value": "9512466500"
      } ],
      "address": [ {
        "line": [ "35470 WHITEWOOD RD" ],
        "city": "MURRIETA",
        "state": "CA",
        "postalCode": "925632415",
        "country": "US"
      } ]
    },
    "request": {
      "method": "POST",
      "url": "Organization",
      "ifNoneExist": "identifier=https://github.com/synthetichealth/synthea|dbbc5a45-af78-3aec-a0b3-d779cf9c325e"
    }
  }, {
    "fullUrl": "urn:uuid:8d7897d9-2edc-3051-94d1-6a25f178f383",
    "resource": {
      "resourceType": "Location",
      "id": "8d7897d9-2edc-3051-94d1-6a25f178f383",
      "meta": {
        "profile": [ "http://hl7.org/fhir/us/core/StructureDefinition/us-core-location" ]
      },
      "identifier": [ {
        "system": "https://github.com/synthetichealth/synthea",
        "value": "8d7897d9-2edc-3051-94d1-6a25f178f383"
      } ],
      "status": "active",
      "name": "ENCOMPASS HEALTH REHABILITATION HOSPITAL OF MURRIETA, LLC",
      "telecom": [ {
        "system": "phone",
        "value": "9512466500"
      } ],
      "address": {
        "line": [ "35470 WHITEWOOD RD" ],
        "city": "MURRIETA",
        "state": "CA",
        "postalCode": "925632415",
        "country": "US"
      },
      "position": {
        "longitude": -117.16275562852013,
        "latitude": 33.61052474534199
      },
      "managingOrganization": {
        "identifier": {
          "system": "https://github.com/synthetichealth/synthea",
          "value": "dbbc5a45-af78-3aec-a0b3-d779cf9c325e"
        },
        "display": "ENCOMPASS HEALTH REHABILITATION HOSPITAL OF MURRIETA, LLC"
      }
    },
    "request": {
      "method": "POST",
      "url": "Location",
      "ifNoneExist": "identifier=https://github.com/synthetichealth/synthea|8d7897d9-2edc-3051-94d1-6a25f178f383"
    }
  }, {
    "fullUrl": "urn:uuid:e4f922eb-a9c2-3360-b57e-ef988c9cb5cf",
    "resource": {
      "resourceType": "Organization",
      "id": "e4f922eb-a9c2-3360-b57e-ef988c9cb5cf",
      "meta": {
        "profile": [ "http://hl7.org/fhir/us/core/StructureDefinition/us-core-organization" ]
      },
      "extension": [ {
        "url": "http://synthetichealth.github.io/synthea/utilization-encounters-extension",
        "valueInteger": 43
      }, {
        "url": "http://synthetichealth.github.io/synthea/utilization-procedures-extension",
        "valueInteger": 392
      }, {
        "url": "http://synthetichealth.github.io/synthea/utilization-labs-extension",
        "valueInteger": 91
      }, {
        "url": "http://synthetichealth.github.io/synthea/utilization-prescriptions-extension",
        "valueInteger": 38
      } ],
      "identifier": [ {
        "system": "https://github.com/synthetichealth/synthea",
        "value": "e4f922eb-a9c2-3360-b57e-ef988c9cb5cf"
      } ],
      "active": true,
      "type": [ {
        "coding": [ {
          "system": "http://terminology.hl7.org/CodeSystem/organization-type",
          "code": "prov",
          "display": "Healthcare Provider"
        } ],
        "text": "Healthcare Provider"
      } ],
      "name": "EAST LOS ANGELES ENT MEDICAL CENTER",
      "telecom": [ {
        "system": "phone",
        "value": "6262842000"
      } ],
      "address": [ {
        "line": [ "416 W LAS TUNAS DR" ],
        "city": "SAN GABRIEL",
        "state": "CA",
        "postalCode": "917761133",
        "country": "US"
      } ]
    },
    "request": {
      "method": "POST",
      "url": "Organization",
      "ifNoneExist": "identifier=https://github.com/synthetichealth/synthea|e4f922eb-a9c2-3360-b57e-ef988c9cb5cf"
    }
  }, {
    "fullUrl": "urn:uuid:0f44918b-20a0-3665-96f7-694b0f03433c",
    "resource": {
      "resourceType": "Location",
      "id": "0f44918b-20a0-3665-96f7-694b0f03433c",
      "meta": {
        "profile": [ "http://hl7.org/fhir/us/core/StructureDefinition/us-core-location" ]
      },
      "identifier": [ {
        "system": "https://github.com/synthetichealth/synthea",
        "value": "0f44918b-20a0-3665-96f7-694b0f03433c"
      } ],
      "status": "active",
      "name": "EAST LOS ANGELES ENT MEDICAL CENTER",
      "telecom": [ {
        "system": "phone",
        "value": "6262842000"
      } ],
      "address": {
        "line": [ "416 W LAS TUNAS DR" ],
        "city": "SAN GABRIEL",
        "state": "CA",
        "postalCode": "917761133",
        "country": "US"
      },
      "position": {
        "longitude": -118.1046952,
        "latitude": 34.102044
      },
      "managingOrganization": {
        "identifier": {
          "system": "https://github.com/synthetichealth/synthea",
          "value": "e4f922eb-a9c2-3360-b57e-ef988c9cb5cf"
        },
        "display": "EAST LOS ANGELES ENT MEDICAL CENTER"
      }
    },
    "request": {
      "method": "POST",
      "url": "Location",
      "ifNoneExist": "identifier=https://github.com/synthetichealth/synthea|0f44918b-20a0-3665-96f7-694b0f03433c"
    }
  }, {
    "fullUrl": "urn:uuid:9a3cf483-b0da-37c5-bee7-244896c91310",
    "resource": {
      "resourceType": "Organization",
      "id": "9a3cf483-b0da-37c5-bee7-244896c91310",
      "meta": {
        "profile": [ "http://hl7.org/fhir/us/core/StructureDefinition/us-core-organization" ]
      },
      "extension": [ {
        "url": "http://synthetichealth.github.io/synthea/utilization-encounters-extension",
        "valueInteger": 1
      }, {
        "url": "http://synthetichealth.github.io/synthea/utilization-procedures-extension",
        "valueInteger": 0
      }, {
        "url": "http://synthetichealth.github.io/synthea/utilization-labs-extension",
        "valueInteger": 0
      }, {
        "url": "http://synthetichealth.github.io/synthea/utilization-prescriptions-extension",
        "valueInteger": 0
      } ],
      "identifier": [ {
        "system": "https://github.com/synthetichealth/synthea",
        "value": "9a3cf483-b0da-37c5-bee7-244896c91310"
      } ],
      "active": true,
      "type": [ {
        "coding": [ {
          "system": "http://terminology.hl7.org/CodeSystem/organization-type",
          "code": "prov",
          "display": "Healthcare Provider"
        } ],
        "text": "Healthcare Provider"
      } ],
      "name": "BAYSIDE URGENT CARE AND FAMILY MEDICAL CLINIC PC",
      "telecom": [ {
        "system": "phone",
        "value": "6503682888"
      } ],
      "address": [ {
        "line": [ "39 BIRCH ST STE A" ],
        "city": "REDWOOD CITY",
        "state": "CA",
        "postalCode": "940621483",
        "country": "US"
      } ]
    },
    "request": {
      "method": "POST",
      "url": "Organization",
      "ifNoneExist": "identifier=https://github.com/synthetichealth/synthea|9a3cf483-b0da-37c5-bee7-244896c91310"
    }
  }, {
    "fullUrl": "urn:uuid:4c70d429-9ae5-309a-9b7c-d9c786a05df8",
    "resource": {
      "resourceType": "Location",
      "id": "4c70d429-9ae5-309a-9b7c-d9c786a05df8",
      "meta": {
        "profile": [ "http://hl7.org/fhir/us/core/StructureDefinition/us-core-location" ]
      },
      "identifier": [ {
        "system": "https://github.com/synthetichealth/synthea",
        "value": "4c70d429-9ae5-309a-9b7c-d9c786a05df8"
      } ],
      "status": "active",
      "name": "BAYSIDE URGENT CARE AND FAMILY MEDICAL CLINIC PC",
      "telecom": [ {
        "system": "phone",
        "value": "6503682888"
      } ],
      "address": {
        "line": [ "39 BIRCH ST STE A" ],
        "city": "REDWOOD CITY",
        "state": "CA",
        "postalCode": "940621483",
        "country": "US"
      },
      "position": {
        "longitude": -122.24037725,
        "latitude": 37.48862905
      },
      "managingOrganization": {
        "identifier": {
          "system": "https://github.com/synthetichealth/synthea",
          "value": "9a3cf483-b0da-37c5-bee7-244896c91310"
        },
        "display": "BAYSIDE URGENT CARE AND FAMILY MEDICAL CLINIC PC"
      }
    },
    "request": {
      "method": "POST",
      "url": "Location",
      "ifNoneExist": "identifier=https://github.com/synthetichealth/synthea|4c70d429-9ae5-309a-9b7c-d9c786a05df8"
    }
  }, {
    "fullUrl": "urn:uuid:e54cf3bf-734d-38e7-bfac-74960d568430",
    "resource": {
      "resourceType": "Organization",
      "id": "e54cf3bf-734d-38e7-bfac-74960d568430",
      "meta": {
        "profile": [ "http://hl7.org/fhir/us/core/StructureDefinition/us-core-organization" ]
      },
      "extension": [ {
        "url": "http://synthetichealth.github.io/synthea/utilization-encounters-extension",
        "valueInteger": 3
      }, {
        "url": "http://synthetichealth.github.io/synthea/utilization-procedures-extension",
        "valueInteger": 0
      }, {
        "url": "http://synthetichealth.github.io/synthea/utilization-labs-extension",
        "valueInteger": 0
      }, {
        "url": "http://synthetichealth.github.io/synthea/utilization-prescriptions-extension",
        "valueInteger": 0
      }, {
        "url": "http://synthetichealth.github.io/synthea/bed-count-extension",
        "valueInteger": 44
      } ],
      "identifier": [ {
        "system": "https://github.com/synthetichealth/synthea",
        "value": "e54cf3bf-734d-38e7-bfac-74960d568430"
      } ],
      "active": true,
      "type": [ {
        "coding": [ {
          "system": "http://terminology.hl7.org/CodeSystem/organization-type",
          "code": "prov",
          "display": "Healthcare Provider"
        } ],
        "text": "Healthcare Provider"
      } ],
      "name": "VI AT PALO ALTO",
      "telecom": [ {
        "system": "phone",
        "value": "6508535001"
      } ],
      "address": [ {
        "line": [ "600 SAND HILL ROAD" ],
        "city": "PALO ALTO",
        "state": "CA",
        "postalCode": "943042630",
        "country": "US"
      } ]
    },
    "request": {
      "method": "POST",
      "url": "Organization",
      "ifNoneExist": "identifier=https://github.com/synthetichealth/synthea|e54cf3bf-734d-38e7-bfac-74960d568430"
    }
  }, {
    "fullUrl": "urn:uuid:4ccdf9d9-8b2e-389d-926b-21afe5ec4c26",
    "resource": {
      "resourceType": "Location",
      "id": "4ccdf9d9-8b2e-389d-926b-21afe5ec4c26",
      "meta": {
        "profile": [ "http://hl7.org/fhir/us/core/StructureDefinition/us-core-location" ]
      },
      "identifier": [ {
        "system": "https://github.com/synthetichealth/synthea",
        "value": "4ccdf9d9-8b2e-389d-926b-21afe5ec4c26"
      } ],
      "status": "active",
      "name": "VI AT PALO ALTO",
      "telecom": [ {
        "system": "phone",
        "value": "6508535001"
      } ],
      "address": {
        "line": [ "600 SAND HILL ROAD" ],
        "city": "PALO ALTO",
        "state": "CA",
        "postalCode": "943042630",
        "country": "US"
      },
      "position": {
        "longitude": -122.17513545564728,
        "latitude": 37.43981425369107
      },
      "managingOrganization": {
        "identifier": {
          "system": "https://github.com/synthetichealth/synthea",
          "value": "e54cf3bf-734d-38e7-bfac-74960d568430"
        },
        "display": "VI AT PALO ALTO"
      }
    },
    "request": {
      "method": "POST",
      "url": "Location",
      "ifNoneExist": "identifier=https://github.com/synthetichealth/synthea|4ccdf9d9-8b2e-389d-926b-21afe5ec4c26"
    }
  }, {
    "fullUrl": "urn:uuid:8efb5fec-b267-31d2-8468-f5dcba69b083",
    "resource": {
      "resourceType": "Organization",
      "id": "8efb5fec-b267-31d2-8468-f5dcba69b083",
      "meta": {
        "profile": [ "http://hl7.org/fhir/us/core/StructureDefinition/us-core-organization" ]
      },
      "extension": [ {
        "url": "http://synthetichealth.github.io/synthea/utilization-encounters-extension",
        "valueInteger": 5
      }, {
        "url": "http://synthetichealth.github.io/synthea/utilization-procedures-extension",
        "valueInteger": 0
      }, {
        "url": "http://synthetichealth.github.io/synthea/utilization-labs-extension",
        "valueInteger": 0
      }, {
        "url": "http://synthetichealth.github.io/synthea/utilization-prescriptions-extension",
        "valueInteger": 0
      } ],
      "identifier": [ {
        "system": "https://github.com/synthetichealth/synthea",
        "value": "8efb5fec-b267-31d2-8468-f5dcba69b083"
      } ],
      "active": true,
      "type": [ {
        "coding": [ {
          "system": "http://terminology.hl7.org/CodeSystem/organization-type",
          "code": "prov",
          "display": "Healthcare Provider"
        } ],
        "text": "Healthcare Provider"
      } ],
      "name": "ALTAMED MEDICAL AND DENTAL GROUP - SANTA ANA, MAIN",
      "telecom": [ {
        "system": "phone",
        "value": "7145416815"
      } ],
      "address": [ {
        "line": [ "1400 N MAIN STREET" ],
        "city": "SANTA ANA",
        "state": "CA",
        "postalCode": "927012304",
        "country": "US"
      } ]
    },
    "request": {
      "method": "POST",
      "url": "Organization",
      "ifNoneExist": "identifier=https://github.com/synthetichealth/synthea|8efb5fec-b267-31d2-8468-f5dcba69b083"
    }
  }, {
    "fullUrl": "urn:uuid:684b3cc6-f008-3fcc-9100-f8c28919aff6",
    "resource": {
      "resourceType": "Location",
      "id": "684b3cc6-f008-3fcc-9100-f8c28919aff6",
      "meta": {
        "profile": [ "http://hl7.org/fhir/us/core/StructureDefinition/us-core-location" ]
      },
      "identifier": [ {
        "system": "https://github.com/synthetichealth/synthea",
        "value": "684b3cc6-f008-3fcc-9100-f8c28919aff6"
      } ],
      "status": "active",
      "name": "ALTAMED MEDICAL AND DENTAL GROUP - SANTA ANA, MAIN",
      "telecom": [ {
        "system": "phone",
        "value": "7145416815"
      } ],
      "address": {
        "line": [ "1400 N MAIN STREET" ],
        "city": "SANTA ANA",
        "state": "CA",
        "postalCode": "927012304",
        "country": "US"
      },
      "position": {
        "longitude": -117.86769,
        "latitude": 33.756854
      },
      "managingOrganization": {
        "identifier": {
          "system": "https://github.com/synthetichealth/synthea",
          "value": "8efb5fec-b267-31d2-8468-f5dcba69b083"
        },
        "display": "ALTAMED MEDICAL AND DENTAL GROUP - SANTA ANA, MAIN"
      }
    },
    "request": {
      "method": "POST",
      "url": "Location",
      "ifNoneExist": "identifier=https://github.com/synthetichealth/synthea|684b3cc6-f008-3fcc-9100-f8c28919aff6"
    }
  }, {
    "fullUrl": "urn:uuid:5f0f4d2f-3fb0-3634-918b-5fbefdb929a1",
    "resource": {
      "resourceType": "Organization",
      "id": "5f0f4d2f-3fb0-3634-918b-5fbefdb929a1",
      "meta": {
        "profile": [ "http://hl7.org/fhir/us/core/StructureDefinition/us-core-organization" ]
      },
      "extension": [ {
        "url": "http://synthetichealth.github.io/synthea/utilization-encounters-extension",
        "valueInteger": 1
      }, {
        "url": "http://synthetichealth.github.io/synthea/utilization-procedures-extension",
        "valueInteger": 0
      }, {
        "url": "http://synthetichealth.github.io/synthea/utilization-labs-extension",
        "valueInteger": 0
      }, {
        "url": "http://synthetichealth.github.io/synthea/utilization-prescriptions-extension",
        "valueInteger": 0
      } ],
      "identifier": [ {
        "system": "https://github.com/synthetichealth/synthea",
        "value": "5f0f4d2f-3fb0-3634-918b-5fbefdb929a1"
      } ],
      "active": true,
      "type": [ {
        "coding": [ {
          "system": "http://terminology.hl7.org/CodeSystem/organization-type",
          "code": "prov",
          "display": "Healthcare Provider"
        } ],
        "text": "Healthcare Provider"
      } ],
      "name": "SOLAR URGENT CARE INC",
      "telecom": [ {
        "system": "phone",
        "value": "8059889000"
      } ],
      "address": [ {
        "line": [ "2100 SOLAR DR STE 100" ],
        "city": "OXNARD",
        "state": "CA",
        "postalCode": "930360647",
        "country": "US"
      } ]
    },
    "request": {
      "method": "POST",
      "url": "Organization",
      "ifNoneExist": "identifier=https://github.com/synthetichealth/synthea|5f0f4d2f-3fb0-3634-918b-5fbefdb929a1"
    }
  }, {
    "fullUrl": "urn:uuid:42378cc5-744e-3b6e-9feb-851fbb1064ee",
    "resource": {
      "resourceType": "Location",
      "id": "42378cc5-744e-3b6e-9feb-851fbb1064ee",
      "meta": {
        "profile": [ "http://hl7.org/fhir/us/core/StructureDefinition/us-core-location" ]
      },
      "identifier": [ {
        "system": "https://github.com/synthetichealth/synthea",
        "value": "42378cc5-744e-3b6e-9feb-851fbb1064ee"
      } ],
      "status": "active",
      "name": "SOLAR URGENT CARE INC",
      "telecom": [ {
        "system": "phone",
        "value": "8059889000"
      } ],
      "address": {
        "line": [ "2100 SOLAR DR STE 100" ],
        "city": "OXNARD",
        "state": "CA",
        "postalCode": "930360647",
        "country": "US"
      },
      "position": {
        "longitude": -119.1447837998898,
        "latitude": 34.22064334205796
      },
      "managingOrganization": {
        "identifier": {
          "system": "https://github.com/synthetichealth/synthea",
          "value": "5f0f4d2f-3fb0-3634-918b-5fbefdb929a1"
        },
        "display": "SOLAR URGENT CARE INC"
      }
    },
    "request": {
      "method": "POST",
      "url": "Location",
      "ifNoneExist": "identifier=https://github.com/synthetichealth/synthea|42378cc5-744e-3b6e-9feb-851fbb1064ee"
    }
  }, {
    "fullUrl": "urn:uuid:6e12246a-4da2-3a99-9de5-941a30921175",
    "resource": {
      "resourceType": "Organization",
      "id": "6e12246a-4da2-3a99-9de5-941a30921175",
      "meta": {
        "profile": [ "http://hl7.org/fhir/us/core/StructureDefinition/us-core-organization" ]
      },
      "extension": [ {
        "url": "http://synthetichealth.github.io/synthea/utilization-encounters-extension",
        "valueInteger": 33
      }, {
        "url": "http://synthetichealth.github.io/synthea/utilization-procedures-extension",
        "valueInteger": 149
      }, {
        "url": "http://synthetichealth.github.io/synthea/utilization-labs-extension",
        "valueInteger": 38
      }, {
        "url": "http://synthetichealth.github.io/synthea/utilization-prescriptions-extension",
        "valueInteger": 13
      } ],
      "identifier": [ {
        "system": "https://github.com/synthetichealth/synthea",
        "value": "6e12246a-4da2-3a99-9de5-941a30921175"
      } ],
      "active": true,
      "type": [ {
        "coding": [ {
          "system": "http://terminology.hl7.org/CodeSystem/organization-type",
          "code": "prov",
          "display": "Healthcare Provider"
        } ],
        "text": "Healthcare Provider"
      } ],
      "name": "MURRIETA PRIMARY CARE CLINIC",
      "telecom": [ {
        "system": "phone",
        "value": "8183706581"
      } ],
      "address": [ {
        "line": [ "29995 TECHNOLOGY DR STE 202" ],
        "city": "MURRIETA",
        "state": "CA",
        "postalCode": "925632632",
        "country": "US"
      } ]
    },
    "request": {
      "method": "POST",
      "url": "Organization",
      "ifNoneExist": "identifier=https://github.com/synthetichealth/synthea|6e12246a-4da2-3a99-9de5-941a30921175"
    }
  }, {
    "fullUrl": "urn:uuid:fa834852-ac55-3697-8a43-a1eaff63b329",
    "resource": {
      "resourceType": "Location",
      "id": "fa834852-ac55-3697-8a43-a1eaff63b329",
      "meta": {
        "profile": [ "http://hl7.org/fhir/us/core/StructureDefinition/us-core-location" ]
      },
      "identifier": [ {
        "system": "https://github.com/synthetichealth/synthea",
        "value": "fa834852-ac55-3697-8a43-a1eaff63b329"
      } ],
      "status": "active",
      "name": "MURRIETA PRIMARY CARE CLINIC",
      "telecom": [ {
        "system": "phone",
        "value": "8183706581"
      } ],
      "address": {
        "line": [ "29995 TECHNOLOGY DR STE 202" ],
        "city": "MURRIETA",
        "state": "CA",
        "postalCode": "925632632",
        "country": "US"
      },
      "position": {
        "longitude": -117.1387407,
        "latitude": 33.5607933
      },
      "managingOrganization": {
        "identifier": {
          "system": "https://github.com/synthetichealth/synthea",
          "value": "6e12246a-4da2-3a99-9de5-941a30921175"
        },
        "display": "MURRIETA PRIMARY CARE CLINIC"
      }
    },
    "request": {
      "method": "POST",
      "url": "Location",
      "ifNoneExist": "identifier=https://github.com/synthetichealth/synthea|fa834852-ac55-3697-8a43-a1eaff63b329"
    }
  }, {
    "fullUrl": "urn:uuid:217df740-9975-318b-a9bc-e15435bf923e",
    "resource": {
      "resourceType": "Organization",
      "id": "217df740-9975-318b-a9bc-e15435bf923e",
      "meta": {
        "profile": [ "http://hl7.org/fhir/us/core/StructureDefinition/us-core-organization" ]
      },
      "extension": [ {
        "url": "http://synthetichealth.github.io/synthea/utilization-encounters-extension",
        "valueInteger": 104
      }, {
        "url": "http://synthetichealth.github.io/synthea/utilization-procedures-extension",
        "valueInteger": 0
      }, {
        "url": "http://synthetichealth.github.io/synthea/utilization-labs-extension",
        "valueInteger": 0
      }, {
        "url": "http://synthetichealth.github.io/synthea/utilization-prescriptions-extension",
        "valueInteger": 0
      }, {
        "url": "http://synthetichealth.github.io/synthea/bed-count-extension",
        "valueInteger": 396
      } ],
      "identifier": [ {
        "system": "https://github.com/synthetichealth/synthea",
        "value": "217df740-9975-318b-a9bc-e15435bf923e"
      } ],
      "active": true,
      "type": [ {
        "coding": [ {
          "system": "http://terminology.hl7.org/CodeSystem/organization-type",
          "code": "prov",
          "display": "Healthcare Provider"
        } ],
        "text": "Healthcare Provider"
      } ],
      "name": "LUCILE SALTER PACKARD CHILDREN'S HSP AT STANFORD",
      "telecom": [ {
        "system": "phone",
        "value": "6504978000"
      } ],
      "address": [ {
        "line": [ "725 WELCH ROAD" ],
        "city": "STANFORD",
        "state": "CA",
        "postalCode": "943052200",
        "country": "US"
      } ]
    },
    "request": {
      "method": "POST",
      "url": "Organization",
      "ifNoneExist": "identifier=https://github.com/synthetichealth/synthea|217df740-9975-318b-a9bc-e15435bf923e"
    }
  }, {
    "fullUrl": "urn:uuid:cd7cc9ca-f77b-3bff-8a64-3eacf699a45e",
    "resource": {
      "resourceType": "Location",
      "id": "cd7cc9ca-f77b-3bff-8a64-3eacf699a45e",
      "meta": {
        "profile": [ "http://hl7.org/fhir/us/core/StructureDefinition/us-core-location" ]
      },
      "identifier": [ {
        "system": "https://github.com/synthetichealth/synthea",
        "value": "cd7cc9ca-f77b-3bff-8a64-3eacf699a45e"
      } ],
      "status": "active",
      "name": "LUCILE SALTER PACKARD CHILDREN'S HSP AT STANFORD",
      "telecom": [ {
        "system": "phone",
        "value": "6504978000"
      } ],
      "address": {
        "line": [ "725 WELCH ROAD" ],
        "city": "STANFORD",
        "state": "CA",
        "postalCode": "943052200",
        "country": "US"
      },
      "position": {
        "longitude": -122.1752510159896,
        "latitude": 37.436156749999995
      },
      "managingOrganization": {
        "identifier": {
          "system": "https://github.com/synthetichealth/synthea",
          "value": "217df740-9975-318b-a9bc-e15435bf923e"
        },
        "display": "LUCILE SALTER PACKARD CHILDREN'S HSP AT STANFORD"
      }
    },
    "request": {
      "method": "POST",
      "url": "Location",
      "ifNoneExist": "identifier=https://github.com/synthetichealth/synthea|cd7cc9ca-f77b-3bff-8a64-3eacf699a45e"
    }
  }, {
    "fullUrl": "urn:uuid:9cb94a89-7849-3a12-bb4f-0889ffe4d931",
    "resource": {
      "resourceType": "Organization",
      "id": "9cb94a89-7849-3a12-bb4f-0889ffe4d931",
      "meta": {
        "profile": [ "http://hl7.org/fhir/us/core/StructureDefinition/us-core-organization" ]
      },
      "extension": [ {
        "url": "http://synthetichealth.github.io/synthea/utilization-encounters-extension",
        "valueInteger": 29
      }, {
        "url": "http://synthetichealth.github.io/synthea/utilization-procedures-extension",
        "valueInteger": 209
      }, {
        "url": "http://synthetichealth.github.io/synthea/utilization-labs-extension",
        "valueInteger": 21
      }, {
        "url": "http://synthetichealth.github.io/synthea/utilization-prescriptions-extension",
        "valueInteger": 21
      } ],
      "identifier": [ {
        "system": "https://github.com/synthetichealth/synthea",
        "value": "9cb94a89-7849-3a12-bb4f-0889ffe4d931"
      } ],
      "active": true,
      "type": [ {
        "coding": [ {
          "system": "http://terminology.hl7.org/CodeSystem/organization-type",
          "code": "prov",
          "display": "Healthcare Provider"
        } ],
        "text": "Healthcare Provider"
      } ],
      "name": "OC FAMILY MEDICAL GROUP, INC.",
      "telecom": [ {
        "system": "phone",
        "value": "6572364909"
      } ],
      "address": [ {
        "line": [ "2401 W CHAPMAN AVE STE 201" ],
        "city": "ORANGE",
        "state": "CA",
        "postalCode": "928682327",
        "country": "US"
      } ]
    },
    "request": {
      "method": "POST",
      "url": "Organization",
      "ifNoneExist": "identifier=https://github.com/synthetichealth/synthea|9cb94a89-7849-3a12-bb4f-0889ffe4d931"
    }
  }, {
    "fullUrl": "urn:uuid:8193d138-5655-3f15-a031-89dfdbc6b0fc",
    "resource": {
      "resourceType": "Location",
      "id": "8193d138-5655-3f15-a031-89dfdbc6b0fc",
      "meta": {
        "profile": [ "http://hl7.org/fhir/us/core/StructureDefinition/us-core-location" ]
      },
      "identifier": [ {
        "system": "https://github.com/synthetichealth/synthea",
        "value": "8193d138-5655-3f15-a031-89dfdbc6b0fc"
      } ],
      "status": "active",
      "name": "OC FAMILY MEDICAL GROUP, INC.",
      "telecom": [ {
        "system": "phone",
        "value": "6572364909"
      } ],
      "address": {
        "line": [ "2401 W CHAPMAN AVE STE 201" ],
        "city": "ORANGE",
        "state": "CA",
        "postalCode": "928682327",
        "country": "US"
      },
      "position": {
        "longitude": -117.878257,
        "latitude": 33.787969
      },
      "managingOrganization": {
        "identifier": {
          "system": "https://github.com/synthetichealth/synthea",
          "value": "9cb94a89-7849-3a12-bb4f-0889ffe4d931"
        },
        "display": "OC FAMILY MEDICAL GROUP, INC."
      }
    },
    "request": {
      "method": "POST",
      "url": "Location",
      "ifNoneExist": "identifier=https://github.com/synthetichealth/synthea|8193d138-5655-3f15-a031-89dfdbc6b0fc"
    }
  }, {
    "fullUrl": "urn:uuid:1594b52a-957f-3cb4-946e-9178c4172e91",
    "resource": {
      "resourceType": "Organization",
      "id": "1594b52a-957f-3cb4-946e-9178c4172e91",
      "meta": {
        "profile": [ "http://hl7.org/fhir/us/core/StructureDefinition/us-core-organization" ]
      },
      "extension": [ {
        "url": "http://synthetichealth.github.io/synthea/utilization-encounters-extension",
        "valueInteger": 6
      }, {
        "url": "http://synthetichealth.github.io/synthea/utilization-procedures-extension",
        "valueInteger": 4
      }, {
        "url": "http://synthetichealth.github.io/synthea/utilization-labs-extension",
        "valueInteger": 1
      }, {
        "url": "http://synthetichealth.github.io/synthea/utilization-prescriptions-extension",
        "valueInteger": 0
      } ],
      "identifier": [ {
        "system": "https://github.com/synthetichealth/synthea",
        "value": "1594b52a-957f-3cb4-946e-9178c4172e91"
      } ],
      "active": true,
      "type": [ {
        "coding": [ {
          "system": "http://terminology.hl7.org/CodeSystem/organization-type",
          "code": "prov",
          "display": "Healthcare Provider"
        } ],
        "text": "Healthcare Provider"
      } ],
      "name": "TEMECULA FAMILY WELLNESS",
      "telecom": [ {
        "system": "phone",
        "value": "9516943535"
      } ],
      "address": [ {
        "line": [ "27555 YNEZ RD STE 340" ],
        "city": "TEMECULA",
        "state": "CA",
        "postalCode": "925914678",
        "country": "US"
      } ]
    },
    "request": {
      "method": "POST",
      "url": "Organization",
      "ifNoneExist": "identifier=https://github.com/synthetichealth/synthea|1594b52a-957f-3cb4-946e-9178c4172e91"
    }
  }, {
    "fullUrl": "urn:uuid:a34babdb-13ec-322b-b51e-ba9be93e7606",
    "resource": {
      "resourceType": "Location",
      "id": "a34babdb-13ec-322b-b51e-ba9be93e7606",
      "meta": {
        "profile": [ "http://hl7.org/fhir/us/core/StructureDefinition/us-core-location" ]
      },
      "identifier": [ {
        "system": "https://github.com/synthetichealth/synthea",
        "value": "a34babdb-13ec-322b-b51e-ba9be93e7606"
      } ],
      "status": "active",
      "name": "TEMECULA FAMILY WELLNESS",
      "telecom": [ {
        "system": "phone",
        "value": "9516943535"
      } ],
      "address": {
        "line": [ "27555 YNEZ RD STE 340" ],
        "city": "TEMECULA",
        "state": "CA",
        "postalCode": "925914678",
        "country": "US"
      },
      "position": {
        "longitude": -117.1500109352211,
        "latitude": 33.5053218309498
      },
      "managingOrganization": {
        "identifier": {
          "system": "https://github.com/synthetichealth/synthea",
          "value": "1594b52a-957f-3cb4-946e-9178c4172e91"
        },
        "display": "TEMECULA FAMILY WELLNESS"
      }
    },
    "request": {
      "method": "POST",
      "url": "Location",
      "ifNoneExist": "identifier=https://github.com/synthetichealth/synthea|a34babdb-13ec-322b-b51e-ba9be93e7606"
    }
  }, {
    "fullUrl": "urn:uuid:d2d1eea7-c68a-39f6-976e-147c9ee92b2f",
    "resource": {
      "resourceType": "Organization",
      "id": "d2d1eea7-c68a-39f6-976e-147c9ee92b2f",
      "meta": {
        "profile": [ "http://hl7.org/fhir/us/core/StructureDefinition/us-core-organization" ]
      },
      "extension": [ {
        "url": "http://synthetichealth.github.io/synthea/utilization-encounters-extension",
        "valueInteger": 2
      }, {
        "url": "http://synthetichealth.github.io/synthea/utilization-procedures-extension",
        "valueInteger": 0
      }, {
        "url": "http://synthetichealth.github.io/synthea/utilization-labs-extension",
        "valueInteger": 0
      }, {
        "url": "http://synthetichealth.github.io/synthea/utilization-prescriptions-extension",
        "valueInteger": 0
      } ],
      "identifier": [ {
        "system": "https://github.com/synthetichealth/synthea",
        "value": "d2d1eea7-c68a-39f6-976e-147c9ee92b2f"
      } ],
      "active": true,
      "type": [ {
        "coding": [ {
          "system": "http://terminology.hl7.org/CodeSystem/organization-type",
          "code": "prov",
          "display": "Healthcare Provider"
        } ],
        "text": "Healthcare Provider"
      } ],
      "name": "TEMECULA PRIMARY CARE",
      "telecom": [ {
        "system": "phone",
        "value": "9512256400"
      } ],
      "address": [ {
        "line": [ "41840 ENTERPRISE NORTH CIRCLE" ],
        "city": "TEMECULA",
        "state": "CA",
        "postalCode": "925905654",
        "country": "US"
      } ]
    },
    "request": {
      "method": "POST",
      "url": "Organization",
      "ifNoneExist": "identifier=https://github.com/synthetichealth/synthea|d2d1eea7-c68a-39f6-976e-147c9ee92b2f"
    }
  }, {
    "fullUrl": "urn:uuid:ea175bac-509d-3e53-b116-a3f3d4a89781",
    "resource": {
      "resourceType": "Location",
      "id": "ea175bac-509d-3e53-b116-a3f3d4a89781",
      "meta": {
        "profile": [ "http://hl7.org/fhir/us/core/StructureDefinition/us-core-location" ]
      },
      "identifier": [ {
        "system": "https://github.com/synthetichealth/synthea",
        "value": "ea175bac-509d-3e53-b116-a3f3d4a89781"
      } ],
      "status": "active",
      "name": "TEMECULA PRIMARY CARE",
      "telecom": [ {
        "system": "phone",
        "value": "9512256400"
      } ],
      "address": {
        "line": [ "41840 ENTERPRISE NORTH CIRCLE" ],
        "city": "TEMECULA",
        "state": "CA",
        "postalCode": "925905654",
        "country": "US"
      },
      "position": {
        "longitude": -117.16984281945294,
        "latitude": 33.51761873434058
      },
      "managingOrganization": {
        "identifier": {
          "system": "https://github.com/synthetichealth/synthea",
          "value": "d2d1eea7-c68a-39f6-976e-147c9ee92b2f"
        },
        "display": "TEMECULA PRIMARY CARE"
      }
    },
    "request": {
      "method": "POST",
      "url": "Location",
      "ifNoneExist": "identifier=https://github.com/synthetichealth/synthea|ea175bac-509d-3e53-b116-a3f3d4a89781"
    }
  }, {
    "fullUrl": "urn:uuid:bb1ad573-19b8-9cd8-68fb-0e6f684df992",
    "resource": {
      "resourceType": "Location",
      "id": "bb1ad573-19b8-9cd8-68fb-0e6f684df992",
      "identifier": [ {
        "system": "https://github.com/synthetichealth/synthea",
        "value": "bb1ad573-19b8-9cd8-68fb-0e6f684df992"
      } ],
      "status": "active",
      "description": "Patient's Home",
      "mode": "kind",
      "physicalType": {
        "coding": [ {
          "system": "http://terminology.hl7.org/CodeSystem/location-physical-type",
          "code": "ho",
          "display": "House"
        } ]
      }
    },
    "request": {
      "method": "POST",
      "url": "Location",
      "ifNoneExist": "identifier=https://github.com/synthetichealth/synthea|bb1ad573-19b8-9cd8-68fb-0e6f684df992"
    }
  } ]
}
